{"name":"E-penser","tagline":"Automatic fansite communicating with Youtube API to show E-penser's videos.","body":"# Présentation d'e-penser\r\n e-penser est une chaîne YouTube répondant à certaines questions aux travers de vidéos ludiques permettant de comprendre plus simplement un principe.\r\n Aussi Bruce Benamran, le créateur d'e-penser, est de facto propriétaire du contenu de ce fansite.\r\n\r\n# Présentation du fansite\r\n Ce fansite a pour principe de lister de façons plus simples les vidéos qu'il propose.\r\n \r\n# Installation\r\n Seule la copie du dossier \"e-penser\" sur votre site est nécessaire. Son fonctionnement ne repose que sur l'API YouTube. (Les fichiers README.md et LICENSE.md sont inutiles)\r\n","google":"","note":"Don't delete this file! It's used internally to help with page regeneration."}